<geometry>
    <scene>
        <sound enbl="0" />
        <camera elev="30" rot="-100" />
        <fog enbl="1" dens="0.02" />
    </scene>
    <walls>
        <vertex x="10" z="0" />
        <vertex x="10" z="50" />
        <vertex x="6" z="150" />
        <vertex x="4" z="250" />
        <vertex x="3" z="350" />
        <vertex x="10" z="450" />
        <vertex x="2" z="500" />
        <vertex x="-2" z="500" goal="1"/>
        <vertex x="-10" z="450" />
        <vertex x="-3" z="350" />
        <vertex x="-4" z="250" />
        <vertex x="-6" z="150" />
        <vertex x="-10" z="50" />
        <vertex x="-10" z="0" />
    </walls>
    <obstacles>
        <obstacle type="BOX" w="4" h="4.5" d="1" x="0" y="8" z="495" />
        <obstacle type="BOX" w="4" h="4.5" d="1" x="0" y="2" z="495" />
        <obstacle type="BOX" w="5" h="10" d="1" x="0" y="5" z="50" amp="6" offs="90" />
        <obstacle type="BOX" w="5" h="10" d="1" x="0" y="5" z="75" amp="6" />
        <obstacle type="BOX" w="5" h="10" d="1" x="0" y="5" z="100" amp="6" offs="90" />
        <obstacle type="BOX" w="5" h="10" d="1" x="0" y="5" z="125" amp="6" offs="270" />
        <obstacle type="BOX" w="5" h="10" d="1" x="0" y="5" z="150" amp="6" offs="90" />
        <obstacle type="BOX" w="5" h="10" d="1" x="0" y="5" z="175" amp="6" />
        <obstacle type="BOX" w="5" h="10" d="1" x="0" y="5" z="200" amp="6" offs="90" />

        <obstacle type="CYLINDER" rad="2" h="10" x="0" y="5" z="250" amp="4" />
        <obstacle type="CYLINDER" rad="2" h="10" x="0" y="5" z="262" amp="4" offs="90" />
        <obstacle type="CYLINDER" rad="2" h="10" x="0" y="5" z="275" amp="4" />
        <obstacle type="CYLINDER" rad="2" h="10" x="0" y="5" z="287" amp="4" offs="270" />
        <obstacle type="CYLINDER" rad="2" h="10" x="0" y="5" z="300" amp="4" offs="90" />
        <obstacle type="CYLINDER" rad="2" h="10" x="0" y="5" z="312" amp="4" offs="270" />
        <obstacle type="CYLINDER" rad="2" h="10" x="0" y="5" z="350" amp="4" offs="90" />
        <obstacle type="CYLINDER" rad="2" h="10" x="0" y="5" z="375" amp="4" />
        <obstacle type="CYLINDER" rad="2" h="10" x="0" y="5" z="400" amp="4" offs="90" />
    </obstacles>
    <enemies>
     	<enemy type="CYLINDER" rad="2" h="10" x="0" y="5" z="-250" ampV="4" />
    </enemies>
    <coins ptsSm="1" ptsLg="3" rotV="75">

        <coin x="0" y="1" z="15" />
        <coin x="0.8" y="1.4" z="24" />
        <coin x="3.0" y="2.6" z="33" />
        <coin x="6.0" y="3.8" z="42" />
        <coin x="6.0" y="5.0" z="51" />
        <coin x="6" y="6.2" z="60" />
        <coin x="6" y="7.4" z="69" />
        <coin x="2" y="9.0" z="87" />
        <coin x="-1" y="7.5" z="96" />
        <coin x="-2.3" y="6.0" z="105" />
        <coin x="-2.3" y="4.5" z="114" />
        <coin x="-2.3" y="3.0" z="123" />
        <coin x="-2" y="1" z="132" />
        <coin x="-0.8" y="1" z="141" />
        <coin x="0.3" y="1" z="150" />
        <coin x="2" y="1" z="159" />
	<coin x="2" y="4" z="168" />
	<coin x="2" y="6" z="177" />
	<coin x="2" y="3" z="186" />
	<coin x="-1" y="1" z="195" />
	<coin x="-3" y="1" z="204" />
	<coin x="-1" y="1" z="213" />
	<coin x="0" y="3" z="222" />
	<coin x="0" y="6" z="231" />

	<coin x="0" y="5" z="430" />
	<coin x="0" y="5" z="440" />
	<coin x="0" y="5" z="450" />
	<coin x="0" y="5" z="460" />
	<coin x="0" y="5" z="470" />
	<coin x="0" y="5" z="490" />
    </coins>
</geometry>
